permissions_auditor/__init__.py
permissions_auditor/admin.py
permissions_auditor/apps.py
permissions_auditor/core.py
permissions_auditor/defaults.py
permissions_auditor/forms.py
permissions_auditor/management/__init__.py
permissions_auditor/management/commands/__init__.py
permissions_auditor/management/commands/check_view_permissions.py
permissions_auditor/management/commands/dump_view_permissions.py
permissions_auditor/processors/__init__.py
permissions_auditor/processors/auth_decorators.py
permissions_auditor/processors/auth_mixins.py
permissions_auditor/processors/base.py
permissions_auditor/templates/permissions_auditor/admin/permission_detail.html
permissions_auditor/templates/permissions_auditor/admin/views_index.html
permissions_auditor/tests/__init__.py
permissions_auditor/tests/base.py
permissions_auditor/tests/test_auth_decorator_processors.py
permissions_auditor/tests/test_auth_mixin_processors.py
permissions_auditor/tests/test_base_processors.py
permissions_auditor/tests/test_core.py
permissions_auditor/tests/test_management.py
permissions_auditor/tests/test_settings.py
permissions_auditor/tests/fixtures/__init__.py
permissions_auditor/tests/fixtures/base_views.py
permissions_auditor/tests/fixtures/decorator_views.py
permissions_auditor/tests/fixtures/mixin_views.py
permissions_auditor/tests/fixtures/urls.py
permissions_auditor/tests/fixtures/views.py
django_permissions_auditor-1.2.0.dist-info/LICENSE
django_permissions_auditor-1.2.0.dist-info/METADATA
django_permissions_auditor-1.2.0.dist-info/WHEEL
django_permissions_auditor-1.2.0.dist-info/top_level.txt
django_permissions_auditor-1.2.0.dist-info/RECORD
