Metadata-Version: 2.1
Name: django-permissions-auditor
Version: 1.2.0
Summary: django-permissions-auditor is a tool to audit access control on your django app.
Home-page: https://github.com/AACEngineering/django-permissions-auditor
Author: AAC Engineering
License: MIT
Keywords: django,admin,permissions,audit,auditor
Classifier: Development Status :: 5 - Production/Stable
Classifier: Environment :: Web Environment
Classifier: Intended Audience :: Developers
Classifier: License :: OSI Approved :: MIT License
Classifier: Operating System :: OS Independent
Classifier: Programming Language :: Python :: 3
Classifier: Programming Language :: Python :: 3.7
Classifier: Programming Language :: Python :: 3.8
Classifier: Programming Language :: Python :: 3.9
Classifier: Programming Language :: Python :: 3.10
Classifier: Programming Language :: Python :: 3.11
Classifier: Programming Language :: Python :: 3.12
Classifier: Framework :: Django
Classifier: Framework :: Django :: 2.2
Classifier: Framework :: Django :: 3.2
Classifier: Framework :: Django :: 4.1
Classifier: Framework :: Django :: 4.2
Classifier: Framework :: Django :: 5.0
Classifier: Topic :: Internet :: WWW/HTTP :: Site Management
Classifier: Topic :: Internet :: WWW/HTTP :: Site Management :: Link Checking
Requires-Python: >=3.5
License-File: LICENSE
Requires-Dist: django >=2.1
Requires-Dist: setuptools
